expose_text/__init__.py
expose_text/core.py
expose_text/exceptions.py
expose_text/formats/__init__.py
expose_text/formats/_docx.py
expose_text/formats/_html.py
expose_text/formats/_pdf.py
expose_text/formats/_txt.py
expose_text/formats/_utils.py
expose_text/formats/base.py
expose_text/formats/markup/__init__.py
expose_text/formats/markup/utils.py
expose_text/formats/pdf/__init__.py
expose_text/formats/pdf/auto_pdf.py
expose_text/formats/pdf/pdf2html2pdf.py
expose_text/formats/pdf/pdf_redactor.py
expose_text-0.1.6.dist-info/LICENSE
expose_text-0.1.6.dist-info/METADATA
expose_text-0.1.6.dist-info/WHEEL
expose_text-0.1.6.dist-info/top_level.txt
expose_text-0.1.6.dist-info/RECORD
