Metadata-Version: 2.1
Name: expose-text
Version: 0.1.6
Summary: A Python module that exposes text for modification in multiple file types.
Home-page: https://openredact.org/
Author: Jonas Langhabel, Malte Ostendorff
Author-email: hello@openredact.org
License: MIT
Platform: UNKNOWN
Requires-Python: >=3.7
Requires-Dist: pdfrw (==0.4)
Requires-Dist: defusedxml (==0.6.0)
Requires-Dist: beautifulsoup4 (==4.9.1)
Requires-Dist: wkhtmltopdf (==0.2)
Requires-Dist: pdfkit (==0.6.1)
